optimi/__init__.py
optimi/adam.py
optimi/adamw.py
optimi/adan.py
optimi/gradientrelease.py
optimi/lion.py
optimi/optimizer.py
optimi/radam.py
optimi/ranger.py
optimi/sgd.py
optimi/stableadamw.py
optimi/utils.py
torch_optimi-0.3.3.dist-info/WHEEL
torch_optimi-0.3.3.dist-info/METADATA
torch_optimi-0.3.3.dist-info/RECORD
