Metadata-Version: 2.3
Name: torch-optimi
Version: 0.3.3
Summary: Fast, Modern, & Low Precision PyTorch Optimizers
Keywords: Optimizers,PyTorch,Deep Learning,AI
Author: Benjamin Warner
Author-email: Benjamin Warner <me@benjaminwarner.dev>
License: MIT License
Classifier: Development Status :: 4 - Beta
Classifier: Intended Audience :: Developers
Classifier: License :: OSI Approved :: MIT License
Classifier: Programming Language :: Python :: 3.10
Classifier: Programming Language :: Python :: 3.11
Classifier: Programming Language :: Python :: 3.12
Classifier: Programming Language :: Python :: 3.13
Classifier: Programming Language :: Python :: 3.14
Classifier: Topic :: Scientific/Engineering :: Artificial Intelligence
Requires-Dist: torch>=2.2
Requires-Python: >=3.10
Project-URL: Bug Reports, https://github.com/warner-benjamin/optimi/issues
Project-URL: Homepage, https://optimi.benjaminwarner.dev
Project-URL: Source, https://github.com/warner-benjamin/optimi
